[1,["10p3Yy4hBBHpuDLCs4etgo@6c48a","5flgDYIhdIbZG/w7M9LJC3@6c48a","a29TNyCkZBloJiZfAExQdQ@6c48a","bcswsskSlCa72v2O0XkVir@6c48a","cbowsXDYNIS6oDUOvKhjv2@6c48a","f2Bu3M5/5LO7nixbYshFuX@6c48a"],["_textureSource"],["cc.SpriteFrame"],0,[[[{"name":"RocketSpritesheet_05","rect":{"x":0,"y":0,"width":100,"height":102},"offset":{"x":0,"y":0},"originalSize":{"width":100,"height":102},"rotated":false,"capInsets":[0,0,0,0],"vertices":{"rawPosition":[-50,-51,0,50,-51,0,-50,51,0,50,51,0],"indexes":[0,1,2,2,1,3],"uv":[0,102,100,102,0,0,100,0],"nuv":[0,0,1,0,0,1,1,1],"minPos":{"x":-50,"y":-51,"z":0},"maxPos":{"x":50,"y":51,"z":0}},"packable":true,"pixelsToUnit":100,"pivot":{"x":0.5,"y":0.5},"meshType":0}],[0],0,[0],[0],[0]],[[{"name":"RocketSpritesheet_02","rect":{"x":0,"y":0,"width":100,"height":102},"offset":{"x":0,"y":0},"originalSize":{"width":100,"height":102},"rotated":false,"capInsets":[0,0,0,0],"vertices":{"rawPosition":[-50,-51,0,50,-51,0,-50,51,0,50,51,0],"indexes":[0,1,2,2,1,3],"uv":[0,102,100,102,0,0,100,0],"nuv":[0,0,1,0,0,1,1,1],"minPos":{"x":-50,"y":-51,"z":0},"maxPos":{"x":50,"y":51,"z":0}},"packable":true,"pixelsToUnit":100,"pivot":{"x":0.5,"y":0.5},"meshType":0}],[0],0,[0],[0],[1]],[[{"name":"RocketSpritesheet_00","rect":{"x":0,"y":0,"width":100,"height":102},"offset":{"x":0,"y":0},"originalSize":{"width":100,"height":102},"rotated":false,"capInsets":[0,0,0,0],"vertices":{"rawPosition":[-50,-51,0,50,-51,0,-50,51,0,50,51,0],"indexes":[0,1,2,2,1,3],"uv":[0,102,100,102,0,0,100,0],"nuv":[0,0,1,0,0,1,1,1],"minPos":{"x":-50,"y":-51,"z":0},"maxPos":{"x":50,"y":51,"z":0}},"packable":true,"pixelsToUnit":100,"pivot":{"x":0.5,"y":0.5},"meshType":0}],[0],0,[0],[0],[2]],[[{"name":"RocketSpritesheet_01","rect":{"x":0,"y":0,"width":100,"height":102},"offset":{"x":0,"y":0},"originalSize":{"width":100,"height":102},"rotated":false,"capInsets":[0,0,0,0],"vertices":{"rawPosition":[-50,-51,0,50,-51,0,-50,51,0,50,51,0],"indexes":[0,1,2,2,1,3],"uv":[0,102,100,102,0,0,100,0],"nuv":[0,0,1,0,0,1,1,1],"minPos":{"x":-50,"y":-51,"z":0},"maxPos":{"x":50,"y":51,"z":0}},"packable":true,"pixelsToUnit":100,"pivot":{"x":0.5,"y":0.5},"meshType":0}],[0],0,[0],[0],[3]],[[{"name":"RocketSpritesheet_04","rect":{"x":0,"y":0,"width":100,"height":102},"offset":{"x":0,"y":0},"originalSize":{"width":100,"height":102},"rotated":false,"capInsets":[0,0,0,0],"vertices":{"rawPosition":[-50,-51,0,50,-51,0,-50,51,0,50,51,0],"indexes":[0,1,2,2,1,3],"uv":[0,102,100,102,0,0,100,0],"nuv":[0,0,1,0,0,1,1,1],"minPos":{"x":-50,"y":-51,"z":0},"maxPos":{"x":50,"y":51,"z":0}},"packable":true,"pixelsToUnit":100,"pivot":{"x":0.5,"y":0.5},"meshType":0}],[0],0,[0],[0],[4]],[[{"name":"RocketSpritesheet_03","rect":{"x":0,"y":0,"width":100,"height":102},"offset":{"x":0,"y":0},"originalSize":{"width":100,"height":102},"rotated":false,"capInsets":[0,0,0,0],"vertices":{"rawPosition":[-50,-51,0,50,-51,0,-50,51,0,50,51,0],"indexes":[0,1,2,2,1,3],"uv":[0,102,100,102,0,0,100,0],"nuv":[0,0,1,0,0,1,1,1],"minPos":{"x":-50,"y":-51,"z":0},"maxPos":{"x":50,"y":51,"z":0}},"packable":true,"pixelsToUnit":100,"pivot":{"x":0.5,"y":0.5},"meshType":0}],[0],0,[0],[0],[5]]]]
